[
    {
      "english": "Urban planning is the process of designing and managing cities for the future.",
      "arabic": "تخطيط المدن هو عملية تصميم وإدارة المدن من أجل المستقبل."
    },
    {
      "english": "It considers factors like infrastructure, housing, transportation, and public spaces.",
      "arabic": "ويأخذ بعين الاعتبار عوامل مثل البنية التحتية والإسكان والمواصلات والأماكن العامة."
    },
    {
      "english": "Good urban planning can create sustainable, livable, and resilient cities.",
      "arabic": "يمكن أن يخلق التخطيط الحضري الجيد مدنًا مستدامة وقابلة للعيش ومرنة."
    },
    {
      "english": "Urban planners work with architects, engineers, and other professionals.",
      "arabic": "يعمل مخططو المدن مع المهندسين المعماريين والمهندسين وغيرهم من المهنيين."
    },
    {
      "english": "They consider the needs of residents, businesses, and the environment.",
      "arabic": "يأخذون بعين الاعتبار احتياجات السكان والشركات والبيئة."
    },
    {
      "english": "Some key challenges in urban planning include traffic congestion, affordable housing, and climate change.",
      "arabic": "تشمل بعض التحديات الرئيسية في تخطيط المدن الازدحام المروري والمساكن بأسعار معقولة وتغير المناخ."
    },
    {
      "english": "Smart city initiatives use technology to improve efficiency and sustainability.",
      "arabic": "تستخدم مبادرات المدن الذكية التكنولوجيا لتحسين الكفاءة والاستدامة."
    },
    {
      "english": "Public participation is crucial for creating successful urban plans.",
      "arabic": "المشاركة العامة ضرورية لإنشاء خطط حضرية ناجحة."
    },
    {
      "english": "What aspects of urban planning are you most interested in?",
      "arabic": "ما جوانب تخطيط المدن التي تثير اهتمامك أكثر؟"
    },
    {
      "english": "Urban planning can help create a better quality of life for everyone.",
      "arabic": "يمكن أن يساعد تخطيط المدن في خلق نوعية حياة أفضل للجميع."
    },
    {
      "english": "There are many innovative ideas emerging in urban planning, like green infrastructure and mixed-use development.",
      "arabic": "هناك العديد من الأفكار المبتكرة التي تظهر في تخطيط المدن ، مثل البنية التحتية الخضراء والتطوير متعدد الاستخدامات."
    },
    {
      "english": "Urban planning is constantly evolving to address new challenges and opportunities.",
      "arabic": "يتطور تخطيط المدن باستمرار لمواجهة التحديات والفرص الجديدة."
    },
    {
      "english": "I'd love to hear your ideas for making cities more livable.",
      "arabic": "يسعدني أن أسمع أفكارك حول جعل المدن أكثر قابلية للعيش."
    },
    {
      "english": "Sustainable transportation options like cycling and public transit are important for urban planning.",
      "arabic": "خيارات النقل المستدامة مثل ركوب الدراجات والنقل العام مهمة لتخطيط المدن."
    },
    {
      "english": "Preserving historic buildings and green spaces is also a key consideration.",
      "arabic": "يعتبر الحفاظ على المباني التاريخية والمساحات الخضراء أيضًا من الاعتبارات الرئيسية."
    }
  ]
  
